ClearInsights/ClearInsightsModule.py
ClearInsights/__init__.py
ClearInsights-0.1.9.dist-info/LICENSE
ClearInsights-0.1.9.dist-info/METADATA
ClearInsights-0.1.9.dist-info/WHEEL
ClearInsights-0.1.9.dist-info/top_level.txt
ClearInsights-0.1.9.dist-info/RECORD
