Metadata-Version: 2.1
Name: ClearInsights
Version: 0.1.9
Summary: A portable class Library for the ClearInsights API. (Official Library)
Home-page: https://clearinsights.io
Author: ClearInsights
Author-email: support@clearinsights.io
License: UNKNOWN
Project-URL: Documentation, https://docs.clearinsights.io
Project-URL: Bug Reports, https://clearinsights.io/contact-us/
Keywords: logging,monitoring,insights,application insights,clearinsights
Platform: UNKNOWN
Classifier: Development Status :: 5 - Production/Stable
Classifier: Intended Audience :: Developers
Classifier: Topic :: Software Development :: Build Tools
Classifier: Programming Language :: Python :: 3
Classifier: Programming Language :: Python :: 3.6
Classifier: Programming Language :: Python :: 3.7
Classifier: Programming Language :: Python :: 3.8
Classifier: Programming Language :: Python :: 3.9
Classifier: Programming Language :: Python :: 3 :: Only
Classifier: License :: OSI Approved :: MIT License
Classifier: Operating System :: OS Independent
Requires-Python: >=3.6
License-File: LICENSE
Requires-Dist: requests (>=2.28.1)
Provides-Extra: dev
Requires-Dist: check-manifest ; extra == 'dev'
